xaiographs/__init__.py
xaiographs/fairness.py
xaiographs/__pycache__/__init__.cpython-310.pyc
xaiographs/__pycache__/__init__.cpython-311.pyc
xaiographs/__pycache__/__init__.cpython-312.pyc
xaiographs/__pycache__/__init__.cpython-37.pyc
xaiographs/__pycache__/__init__.cpython-38.pyc
xaiographs/__pycache__/__init__.cpython-39.pyc
xaiographs/__pycache__/fairness.cpython-310.pyc
xaiographs/__pycache__/fairness.cpython-311.pyc
xaiographs/__pycache__/fairness.cpython-312.pyc
xaiographs/__pycache__/fairness.cpython-37.pyc
xaiographs/__pycache__/fairness.cpython-38.pyc
xaiographs/__pycache__/fairness.cpython-39.pyc
xaiographs/common/__init__.py
xaiographs/common/constants.py
xaiographs/common/utils.py
xaiographs/common/__pycache__/__init__.cpython-310.pyc
xaiographs/common/__pycache__/__init__.cpython-311.pyc
xaiographs/common/__pycache__/__init__.cpython-312.pyc
xaiographs/common/__pycache__/__init__.cpython-37.pyc
xaiographs/common/__pycache__/__init__.cpython-38.pyc
xaiographs/common/__pycache__/__init__.cpython-39.pyc
xaiographs/common/__pycache__/constants.cpython-310.pyc
xaiographs/common/__pycache__/constants.cpython-311.pyc
xaiographs/common/__pycache__/constants.cpython-312.pyc
xaiographs/common/__pycache__/constants.cpython-37.pyc
xaiographs/common/__pycache__/constants.cpython-38.pyc
xaiographs/common/__pycache__/constants.cpython-39.pyc
xaiographs/common/__pycache__/utils.cpython-310.pyc
xaiographs/common/__pycache__/utils.cpython-311.pyc
xaiographs/common/__pycache__/utils.cpython-312.pyc
xaiographs/common/__pycache__/utils.cpython-37.pyc
xaiographs/common/__pycache__/utils.cpython-38.pyc
xaiographs/common/__pycache__/utils.cpython-39.pyc
xaiographs/datasets/__init__.py
xaiographs/datasets/datasets.py
xaiographs/datasets/__pycache__/__init__.cpython-310.pyc
xaiographs/datasets/__pycache__/__init__.cpython-311.pyc
xaiographs/datasets/__pycache__/__init__.cpython-312.pyc
xaiographs/datasets/__pycache__/__init__.cpython-37.pyc
xaiographs-2.0.0.dist-info/licenses/LICENSE
xaiographs-2.0.0.dist-info/METADATA
xaiographs-2.0.0.dist-info/WHEEL
xaiographs-2.0.0.dist-info/entry_points.txt
xaiographs-2.0.0.dist-info/top_level.txt
xaiographs-2.0.0.dist-info/RECORD
