Metadata-Version: 2.4
Name: xaiographs
Version: 2.0.0
Summary: Python library providing Explainability & Fairness AI functionalities
Home-page: https://github.com/Telefonica/XAIoGraphs
Author: Telefonica I+D
Author-email: ricardo.moyagarcia@telefonica.com
License: AGPL-3.0 license
Keywords: explainability,fairness,IA,Machine Learning
Requires-Python: >=3.10
License-File: LICENSE
Requires-Dist: numpy<2.0.0,>=1.26.0
Requires-Dist: pandas<3.0.0,>=2.0.0
Requires-Dist: scikit-learn==1.3.2
Requires-Dist: scipy<2.0.0,>=1.11.0
Requires-Dist: tqdm>=4.66.0
Dynamic: author
Dynamic: author-email
Dynamic: description
Dynamic: description-content-type
Dynamic: home-page
Dynamic: keywords
Dynamic: license
Dynamic: license-file
Dynamic: requires-dist
Dynamic: requires-python
Dynamic: summary
